odoo/addons/barcodes_generator_abstract/README.rst
odoo/addons/barcodes_generator_abstract/__init__.py
odoo/addons/barcodes_generator_abstract/__manifest__.py
odoo/addons/barcodes_generator_abstract/demo/res_users.xml
odoo/addons/barcodes_generator_abstract/i18n/am.po
odoo/addons/barcodes_generator_abstract/i18n/barcodes_generator_abstract.pot
odoo/addons/barcodes_generator_abstract/i18n/ca.po
odoo/addons/barcodes_generator_abstract/i18n/de.po
odoo/addons/barcodes_generator_abstract/i18n/el_GR.po
odoo/addons/barcodes_generator_abstract/i18n/es.po
odoo/addons/barcodes_generator_abstract/i18n/es_ES.po
odoo/addons/barcodes_generator_abstract/i18n/fi.po
odoo/addons/barcodes_generator_abstract/i18n/fr.po
odoo/addons/barcodes_generator_abstract/i18n/gl.po
odoo/addons/barcodes_generator_abstract/i18n/hr.po
odoo/addons/barcodes_generator_abstract/i18n/hr_HR.po
odoo/addons/barcodes_generator_abstract/i18n/it.po
odoo/addons/barcodes_generator_abstract/i18n/nl.po
odoo/addons/barcodes_generator_abstract/i18n/nl_NL.po
odoo/addons/barcodes_generator_abstract/i18n/pt.po
odoo/addons/barcodes_generator_abstract/i18n/pt_BR.po
odoo/addons/barcodes_generator_abstract/i18n/pt_PT.po
odoo/addons/barcodes_generator_abstract/i18n/sl.po
odoo/addons/barcodes_generator_abstract/i18n/tr.po
odoo/addons/barcodes_generator_abstract/i18n/zh_CN.po
odoo/addons/barcodes_generator_abstract/models/__init__.py
odoo/addons/barcodes_generator_abstract/models/barcode_generate_mixin.py
odoo/addons/barcodes_generator_abstract/models/barcode_rule.py
odoo/addons/barcodes_generator_abstract/security/res_groups.xml
odoo/addons/barcodes_generator_abstract/static/description/barcode_rule_form_manual.png
odoo/addons/barcodes_generator_abstract/static/description/barcode_rule_form_sequence.png
odoo/addons/barcodes_generator_abstract/static/description/barcode_rule_tree.png
odoo/addons/barcodes_generator_abstract/static/description/icon.png
odoo/addons/barcodes_generator_abstract/views/menu.xml
odoo12_addon_barcodes_generator_abstract-12.0.1.0.4.dist-info/METADATA
odoo12_addon_barcodes_generator_abstract-12.0.1.0.4.dist-info/WHEEL
odoo12_addon_barcodes_generator_abstract-12.0.1.0.4.dist-info/top_level.txt
odoo12_addon_barcodes_generator_abstract-12.0.1.0.4.dist-info/RECORD
